ultramind_gigachat/__init__.py
ultramind_gigachat-0.1.0.dist-info/licenses/LICENSE
ultramind_gigachat-0.1.0.dist-info/METADATA
ultramind_gigachat-0.1.0.dist-info/WHEEL
ultramind_gigachat-0.1.0.dist-info/top_level.txt
ultramind_gigachat-0.1.0.dist-info/RECORD
